{"title": "[\uc18d\ubcf4] \uc678\uc2e0 \u201c\ub7ec\uc2dc\uc544\uad70, \uc6b0\ud06c\ub77c \uc218\ub3c4 \ud0a4\uc608\ud504 \uc9c4\uc785\ud574 \uc804\ud22c \uc911\u201d - \uc774\ub370\uc77c\ub9ac", "title_detail": {"type": "text/plain", "language": null, "base": "https://news.google.com/rss/search?q=%EB%9F%AC%EC%8B%9C%EC%95%84%20%EC%9A%B0%ED%81%AC%EB%9D%BC%EC%9D%B4%EB%82%98%20%22%EC%86%8D%EB%B3%B4%22%20when%3A1h&hl=ko&gl=KR&ceid=KR%3Ako", "value": "[\uc18d\ubcf4] \uc678\uc2e0 \u201c\ub7ec\uc2dc\uc544\uad70, \uc6b0\ud06c\ub77c \uc218\ub3c4 \ud0a4\uc608\ud504 \uc9c4\uc785\ud574 \uc804\ud22c \uc911\u201d - \uc774\ub370\uc77c\ub9ac"}, "links": [{"rel": "alternate", "type": "text/html", "href": "https://www.edaily.co.kr/news/read?newsId=01489126632234456&mediaCodeNo=257"}], "link": "https://www.edaily.co.kr/news/read?newsId=01489126632234456&mediaCodeNo=257", "id": "CAIiEFVIG2H72JYKDjjBmeNzSvYqGQgEKhAIACoHCAowgvDcCjCoxM8BML-iiwI", "guidislink": false, "published": "Sat, 26 Feb 2022 04:46:27 GMT", "published_parsed": [2022, 2, 26, 4, 46, 27, 5, 57, 0], "summary": "<a href=\"https://www.edaily.co.kr/news/read?newsId=01489126632234456&amp;mediaCodeNo=257\" target=\"_blank\">[\uc18d\ubcf4] \uc678\uc2e0 \u201c\ub7ec\uc2dc\uc544\uad70, \uc6b0\ud06c\ub77c \uc218\ub3c4 \ud0a4\uc608\ud504 \uc9c4\uc785\ud574 \uc804\ud22c \uc911\u201d</a>&nbsp;&nbsp;<font color=\"#6f6f6f\">\uc774\ub370\uc77c\ub9ac</font>", "summary_detail": {"type": "text/html", "language": null, "base": "https://news.google.com/rss/search?q=%EB%9F%AC%EC%8B%9C%EC%95%84%20%EC%9A%B0%ED%81%AC%EB%9D%BC%EC%9D%B4%EB%82%98%20%22%EC%86%8D%EB%B3%B4%22%20when%3A1h&hl=ko&gl=KR&ceid=KR%3Ako", "value": "<a href=\"https://www.edaily.co.kr/news/read?newsId=01489126632234456&amp;mediaCodeNo=257\" target=\"_blank\">[\uc18d\ubcf4] \uc678\uc2e0 \u201c\ub7ec\uc2dc\uc544\uad70, \uc6b0\ud06c\ub77c \uc218\ub3c4 \ud0a4\uc608\ud504 \uc9c4\uc785\ud574 \uc804\ud22c \uc911\u201d</a>&nbsp;&nbsp;<font color=\"#6f6f6f\">\uc774\ub370\uc77c\ub9ac</font>"}, "source": {"href": "https://www.edaily.co.kr", "title": "\uc774\ub370\uc77c\ub9ac"}}